{"importBase":"import","nativeBase":"native","name":"main","deps":["internal"],"uuids":["2bfVRAPIpAV4/2S4kij5ZH","b5L7kWEUtEW4suMsXafFxx","ca5fabykJLcZMwAEDC9OQr","0funAYRSNFkqFP13TE8oQT","12Y9dMgWdJKJGmTiZyQR9H@2e76e","23gPuV05dLX4KdP/IP1MSg","24pwTaKGdEbY0aXpIMdeCd","37VTiccqZMpYvdEXW05DRI","3cOftOxWhKh5mTPh3AgZI1","43CdRiDDlDtZqS5lcIXfPm","48O4nIqWtGdKfSZ+v5OMHQ","59lhjlTopMdL8gGHgsjtFh","5aZBY+UfRKrYLtrqNWGyit","5dWbvMTohC1agHwPmOQqc2","61sKyjlKxA95UUJAqbO4S/","643I7Kdi1Pu7yhHISNIiUx","67rqzoVRdJBLOiVPU7XFAM","6fAc9/gb9Kfr1dCvwZaWSA@b47c0@40c10","6fAc9/gb9Kfr1dCvwZaWSA@b47c0@74afd","6fAc9/gb9Kfr1dCvwZaWSA@b47c0@7d38f","6fAc9/gb9Kfr1dCvwZaWSA@b47c0@8fd34","6fAc9/gb9Kfr1dCvwZaWSA@b47c0@bb97f","6fAc9/gb9Kfr1dCvwZaWSA@b47c0@e9a6d","71vuJ/OelOpIkHYNFv4CQS@08c68","78ymd2415EKp0MwByP8aiE","7eayjLzstBaKIYwFyTSVyr","86y4/xtEdEoY6UCxItN5uU@10a81","86y4/xtEdEoY6UCxItN5uU@48b02","86080GT5RLNL1Jcw/3FeBd","87FJ8CZNxPH4d+UAJ1iomV@a09cf","90JNcgo3xPX5efTl3yR45b","9f2QDdIhtPiY8s+6NCQ8g1","b3u7H46RhKeah4yOf3+y6n","baIUdvKGZPgZxNbjWTFuRI","c6b7H2VXRKXqbCNM5hJYo7","caA7nTMlRKIqoHaNAXQ+pE@0687f","caA7nTMlRKIqoHaNAXQ+pE@0b568","caA7nTMlRKIqoHaNAXQ+pE@41ac8","caA7nTMlRKIqoHaNAXQ+pE@bdd91","caA7nTMlRKIqoHaNAXQ+pE@c0364","caA7nTMlRKIqoHaNAXQ+pE@faad7","ccYCEk6z9PyK5Ce4QPf7J1","d0MqyYBeFAkIi762QNy1/B@b47c0@40c10","d0MqyYBeFAkIi762QNy1/B@b47c0@74afd","d0MqyYBeFAkIi762QNy1/B@b47c0@7d38f","d0MqyYBeFAkIi762QNy1/B@b47c0@8fd34","d0MqyYBeFAkIi762QNy1/B@b47c0@bb97f","d0MqyYBeFAkIi762QNy1/B@b47c0@e9a6d","d1/7AIMe1FvbZP0X8GvlfX","d3LyqmfIRMvK7Plzh90oMR","deeNtCTapGNrOvtYRuWOGh","e38fEwe6ZB+pf0jXdhQnTj","ecggrtiCpJdZQpK0aB5p6K","f6CRVVd0lJfI6sdEGTTZBJ","fdjsU2o1RKF5x0TziDw3jI","059ab9fa6","05b0c5aa5","0af132a2b","0af616c2b","0dXkdo8ntA+YuMOnseD4sm","14GzuyRDdBCrA9AHS97oMW","24pwTaKGdEbY0aXpIMdeCd@6c48a","24pwTaKGdEbY0aXpIMdeCd@f9941","364oWblidPsb/ck/7owz76","37VTiccqZMpYvdEXW05DRI@6c48a","3cOftOxWhKh5mTPh3AgZI1@6c48a","43CdRiDDlDtZqS5lcIXfPm@6c48a","48O4nIqWtGdKfSZ+v5OMHQ@6c48a","48O4nIqWtGdKfSZ+v5OMHQ@f9941","4bvqZ8ixBGOLBjpIC9heGO","59lhjlTopMdL8gGHgsjtFh@6c48a","5dWbvMTohC1agHwPmOQqc2@6c48a","5dWbvMTohC1agHwPmOQqc2@f9941","61DxnBtmlHe5QXKhUsv3Ee","61sKyjlKxA95UUJAqbO4S/@6c48a","61sKyjlKxA95UUJAqbO4S/@f9941","643I7Kdi1Pu7yhHISNIiUx@6c48a","643I7Kdi1Pu7yhHISNIiUx@f9941","67w++5SBZNqLkeJssHtBq3","6fAc9/gb9Kfr1dCvwZaWSA@b47c0","71vuJ/OelOpIkHYNFv4CQS@70111","71vuJ/OelOpIkHYNFv4CQS@77085","78ymd2415EKp0MwByP8aiE@6c48a","78ymd2415EKp0MwByP8aiE@f9941","7eayjLzstBaKIYwFyTSVyr@6c48a","86y4/xtEdEoY6UCxItN5uU@7d6ab","86y4/xtEdEoY6UCxItN5uU@b4e6b","87FJ8CZNxPH4d+UAJ1iomV@0b7b5","87FJ8CZNxPH4d+UAJ1iomV@99c21","87FJ8CZNxPH4d+UAJ1iomV@f8f78","89KPtYCI5Dm4W+aU8sa/1u","90JNcgo3xPX5efTl3yR45b@6c48a","90JNcgo3xPX5efTl3yR45b@f9941","9aQkv7UXtJabjY6pBVrPYx","9f2QDdIhtPiY8s+6NCQ8g1@6c48a","9f2QDdIhtPiY8s+6NCQ8g1@f9941","9f7DZ2iw5E6oNaEIB1itxe","a9rY3CH1hAqaHjzHRTknrF","b3u7H46RhKeah4yOf3+y6n@6c48a","b3u7H46RhKeah4yOf3+y6n@f9941","c6b7H2VXRKXqbCNM5hJYo7@6c48a","c6b7H2VXRKXqbCNM5hJYo7@f9941","c6gTBo4x5DoobYLDCUll+p","c7FRPYlhFCWpXltgYZNy0M","c7HMpPxhlKCIXcDfAWI6On","c89m0XNRpI2qEsAhLShXXE","caA7nTMlRKIqoHaNAXQ+pE@2ab3f","ccYCEk6z9PyK5Ce4QPf7J1@6c48a","d0MqyYBeFAkIi762QNy1/B@b47c0","d1/7AIMe1FvbZP0X8GvlfX@6c48a","d1/7AIMe1FvbZP0X8GvlfX@f9941","d3LyqmfIRMvK7Plzh90oMR@6c48a","deeNtCTapGNrOvtYRuWOGh@6c48a","deeNtCTapGNrOvtYRuWOGh@f9941","e38fEwe6ZB+pf0jXdhQnTj@6c48a","e38fEwe6ZB+pf0jXdhQnTj@f9941","e9rW906EpL6I4gy4USwpMH","edOpef2nNK4J4DW4NNWU4t","f6SJZOjTJB/JrJeh5xTdF7","fbr7kw1oBCpJW807FMgV51"],"paths":{"33":["db:/internal/physics/default-physics-material",1],"54":["db:/internal/default_renderpipeline/builtin-forward",0]},"scenes":{"db://assets/Scenes/PlayScene/PlayScene.scene":5,"db://assets/Scenes/MainScene/MainScene.scene":28},"packs":{"059ab9fa6":["65","71","84","94","61","74","76","82","85","67","66","91","70","64","98","100","107","109","111","112","114"],"05b0c5aa5":["59","4","60","5","62","0","63","69","72","73","78","23","80","81","83","26","86","87","88","29","89","90","93","95","96","97","1","102","103","104","35","36","106","37","38","39","40","2","116","117","118","119"],"0af132a2b":["68","75","77","79","17","18","19","20","21","22","28","92","99","101","108","42","43","44","45","46","47","110","113","115"],"0af616c2b":["0","8","13","25","31","6","14","15","24","27","10","9","30","11","7","32","1","34","2","41","48","49","50","51"]},"versions":{"import":[55,"2ff08",56,"bcbb8",57,"c5bff",58,"ce401",3,"8331f",12,"f25a2",16,"7c331",52,"c725d",53,"cceb6",54,"731f4"],"native":[4,"2ebe7",6,"a4b59",0,"19ab9",7,"1e143",8,"a1cce",9,"a4502",10,"efde9",11,"84229",13,"6adc1",14,"b11a6",15,"91872",17,"6f2af",18,"459f6",19,"6a9df",20,"dabf1",21,"ea0b7",22,"9e658",23,"da997",24,"d1998",25,"922db",26,"f7701",27,"dcff1",29,"dc3ad",30,"9dbb8",31,"d1118",32,"e4fe4",1,"cd7c0",34,"9d69c",35,"c5fac",36,"935b9",37,"990e2",38,"935b9",39,"5f86c",40,"5f86c",2,"2f979",41,"0570a",42,"d8477",43,"66393",44,"a5757",45,"2b5b1",46,"8000e",47,"3645b",48,"813df",49,"fff44",50,"f502c",51,"b397e"]},"redirect":[33,"0",105,"0"],"debug":false,"extensionMap":{".cconb":["12","16","3","52","53"]},"hasPreloadScript":true,"types":["cc.RenderPipeline","cc.PhysicsMaterial"]}